csi_images/__init__.py
csi_images/csi_events.py
csi_images/csi_frames.py
csi_images/csi_images.py
csi_images/csi_scans.py
csi_images/csi_tiles.py
csi_images/ocular_files.py
csi_images-3.0.4.dist-info/METADATA
csi_images-3.0.4.dist-info/WHEEL
csi_images-3.0.4.dist-info/licenses/LICENSE
csi_images-3.0.4.dist-info/RECORD
