Metadata-Version: 2.4
Name: csi_images
Version: 3.0.4
Summary: CSI-Cancer image-related data structures and basic processing.
Project-URL: Homepage, https://github.com/CSI-Cancer/csi_images
Project-URL: Issues, https://github.com/CSI-Cancer/csi_images/issues
Author-email: Brian Zhang <8885230+brianjzhang@users.noreply.github.com>
License-File: LICENSE
Classifier: License :: OSI Approved :: MIT License
Classifier: Operating System :: OS Independent
Classifier: Programming Language :: Python :: 3
Requires-Python: >=3.11
Requires-Dist: numpy
Requires-Dist: pandas
Requires-Dist: pyyaml
Requires-Dist: tables
Provides-Extra: imageio
Requires-Dist: aicspylibczi; extra == 'imageio'
Requires-Dist: imageio; extra == 'imageio'
Requires-Dist: opencv-python; extra == 'imageio'
Requires-Dist: pillow; extra == 'imageio'
Requires-Dist: scikit-image; extra == 'imageio'
Requires-Dist: tifffile[codecs]; extra == 'imageio'
Provides-Extra: rds
Requires-Dist: pyreadr; extra == 'rds'
